Metadata-Version: 2.4
Name: ctf-dl
Version: 0.3.3
Summary: Command-line tool to download CTF challenges
Author-email: bjornmorten <bjornmdev@proton.me>
License: MIT
Project-URL: Homepage, https://github.com/bjornmorten/ctf-dl/
Project-URL: Repository, https://github.com/bjornmorten/ctf-dl/
Project-URL: Issues, https://github.com/bjornmorten/ctf-dl/issues
Keywords: ctf,ctf-tools
Classifier: Programming Language :: Python :: 3
Classifier: Programming Language :: Python :: 3.10
Classifier: Programming Language :: Python :: 3.11
Classifier: Programming Language :: Python :: 3.12
Classifier: License :: OSI Approved :: MIT License
Classifier: Operating System :: OS Independent
Requires-Python: >=3.10
License-File: LICENSE
Requires-Dist: ctfbridge>=0.8.3
Requires-Dist: httpx>=0.28.0
Requires-Dist: typer>=0.15.3
Requires-Dist: rich>=14.0.0
Requires-Dist: Jinja2>=3.1.6
Requires-Dist: PyYAML>=6.0.0
Requires-Dist: python-slugify[unidecode]>=8.0.4
Requires-Dist: mdformat==0.7.22
Requires-Dist: mdformat_tables==1.0.0
Provides-Extra: dev
Requires-Dist: pytest>=8.0.0; extra == "dev"
Requires-Dist: pytest-mock>=3.15.0; extra == "dev"
Requires-Dist: ruff>=0.13.0; extra == "dev"
Dynamic: license-file
